big_thing_py/__init__.py
big_thing_py/big_thing.py
big_thing_py/manager_thing.py
big_thing_py/staff_thing.py
big_thing_py/super_thing.py
big_thing_py/common/__init__.py
big_thing_py/common/common.py
big_thing_py/common/error.py
big_thing_py/common/mxtype.py
big_thing_py/common/thread.py
big_thing_py/common/helper/const.py
big_thing_py/common/helper/util.py
big_thing_py/core/__init__.py
big_thing_py/core/argument.py
big_thing_py/core/ble_advertiser.py
big_thing_py/core/ethernet_manager.py
big_thing_py/core/function.py
big_thing_py/core/kvstore_controller.py
big_thing_py/core/mqtt_message.py
big_thing_py/core/request.py
big_thing_py/core/service.py
big_thing_py/core/tag.py
big_thing_py/core/thing.py
big_thing_py/core/value.py
big_thing_py/core/wifi_manager.py
big_thing_py/core/device_model/DeviceObjects.py
big_thing_py/core/device_model/Objects.py
big_thing_py/core/device_model/__init__.py
big_thing_py/core/service_model/Objects.py
big_thing_py/core/service_model/SkillObjects.py
big_thing_py/core/service_model/__init__.py
big_thing_py/core/service_model/enum.py
big_thing_py/manager/__init__.py
big_thing_py/manager/manager_common.py
big_thing_py/super/__init__.py
big_thing_py/super/super_function.py
big_thing_py/super/super_mqtt_message.py
big_thing_py/super/super_request.py
big_thing_py/super/helper/const.py
big_thing_py/super/helper/util.py
big_thing_py/utils/__init__.py
big_thing_py/utils/api_util.py
big_thing_py/utils/arg_parse_util.py
big_thing_py/utils/common_util.py
big_thing_py/utils/exception_util.py
big_thing_py/utils/file_util.py
big_thing_py/utils/json_util.py
big_thing_py/utils/log_util.py
big_thing_py/utils/mqtt_util.py
big_thing_py/utils/rf_util.py
big_thing_py/utils/translate_util.py
big_thing_py/utils/camera/camera_client.py
big_thing_py/utils/camera/camera_source.py
big_thing_py/utils/camera/requirements.txt
big_thing_py/utils/camera/setup.sh
big_thing_py/utils/color/color_converter.py
big_thing_py/utils/color/requirements.txt
big_thing_py-0.4.3.1.post13.dist-info/METADATA
big_thing_py-0.4.3.1.post13.dist-info/WHEEL
big_thing_py-0.4.3.1.post13.dist-info/RECORD
