Metadata-Version: 2.4
Name: big-thing-py
Version: 0.4.3.1.post13
Summary: JOI Smart Device SDK
Author-email: MySmaXLab <mysmaxlab@gmail.com>
Requires-Python: >=3.10
Requires-Dist: aenum
Requires-Dist: bless
Requires-Dist: dbus-next
Requires-Dist: getmac
Requires-Dist: gmqtt
Requires-Dist: jsonschema
Requires-Dist: python-gettext
Requires-Dist: requests
Requires-Dist: termcolor
Requires-Dist: tinykv
Requires-Dist: toml
Requires-Dist: typing-extensions>=4.0
Requires-Dist: uvloop>=0.19.0; sys_platform != 'win32'
Requires-Dist: websockets
Requires-Dist: zeroconf
Provides-Extra: dev
Requires-Dist: pytest; extra == 'dev'
Requires-Dist: pytest-asyncio; extra == 'dev'
Requires-Dist: pytest-timeout; extra == 'dev'
Requires-Dist: tox; extra == 'dev'
